<?xml version="1.0" encoding="utf-8"?>
    <?xml-stylesheet type="text/xsl" href="style.xslt"?>
<results>
  <text>
    <info>
      <title>ИЗМЕНА БЕЗ ИЗМЕННИКА
</title>
      <name>Константин</name>
      <author>Бальмонт</author>
    </info>
    <poem>
      <stanza number="1">
        <line number="1">
          <word number="1395284" pos="PREP">О</word>
          <word number="1395285" pos="None">,</word>
          <word number="1395286" pos="PRED">нет</word>
          <word number="1395287" pos="None">,</word>
          <word number="1395288" pos="NPRO">я</word>
          <word number="1395289" pos="PRCL">не</word>
          <word number="1395290" pos="NOUN">изменник</word>
          <word number="1395291" pos="None">,</word>
        </line>
        <line number="2">
          <word number="1395292" pos="ADJF">Красивые</word>
          <word number="1395293" pos="ADJF">мои</word>
          <word number="1395294" pos="None">.</word>
        </line>
        <line number="3">
          <word number="1395295" pos="NPRO">Я</word>
          <word number="1395296" pos="VERB">был</word>
          <word number="1395297" pos="NPRO">вам</word>
          <word number="1395298" pos="ADJF">верный</word>
          <word number="1395299" pos="NOUN">пленник</word>
          <word number="1395300" pos="None">,</word>
        </line>
        <line number="4">
          <word number="1395301" pos="NPRO">Я</word>
          <word number="1395302" pos="ADJF">ваш</word>
          <word number="1395303" pos="VERB">был</word>
          <word number="1395304" pos="None">,</word>
          <word number="1395305" pos="PREP">в</word>
          <word number="1395306" pos="NOUN">забытьи</word>
          <word number="1395307" pos="None">.</word>
        </line>
      </stanza>
      <stanza number="2">
        <line number="5">
          <word number="1395308" pos="CONJ">Но</word>
          <word number="1395309" pos="None">,</word>
          <word number="1395310" pos="CONJ">ежели</word>
          <word number="1395311" pos="PREP">с</word>
          <word number="1395312" pos="NOUN">царицей</word>
        </line>
        <line number="6">
          <word number="1395313" pos="NPRO">Я</word>
          <word number="1395314" pos="VERB">был</word>
          <word number="1395315" pos="CONJ">и</word>
          <word number="1395316" pos="NOUN">царь</word>
          <word number="1395317" pos="CONJ">и</word>
          <word number="1395318" pos="NOUN">раб</word>
          <word number="1395319" pos="None">,</word>
        </line>
        <line number="7">
          <word number="1395320" pos="VERB">Лечу</word>
          <word number="1395321" pos="NPRO">я</word>
          <word number="1395322" pos="ADJF">вольной</word>
          <word number="1395323" pos="NOUN">птицей</word>
        </line>
        <line number="8">
          <word number="1395324" pos="PREP">Из</word>
          <word number="1395325" pos="NOUN">царства</word>
          <word number="1395326" pos="ADJF">скользких</word>
          <word number="1395327" pos="NOUN">жаб</word>
          <word number="1395328" pos="None">.</word>
        </line>
      </stanza>
      <stanza number="3">
        <line number="9">
          <word number="1395329" pos="NPRO">Я</word>
          <word number="1395330" pos="VERB">был</word>
          <word number="1395331" pos="PRCL">бы</word>
          <word number="1395332" pos="ADJF">вечный</word>
          <word number="1395333" pos="NOUN">пленник</word>
          <word number="1395334" pos="None">,</word>
        </line>
        <line number="10">
          <word number="1395335" pos="ADVB">Всегда</word>
          <word number="1395336" pos="PRCL">б</word>
          <word number="1395337" pos="VERB">склонялся</word>
          <word number="1395338" pos="ADVB">ниц</word>
          <word number="1395339" pos="None">,</word>
        </line>
        <line number="11">
          <word number="1395340" pos="CONJ">Но</word>
          <word number="1395341" pos="VERB">медлит</word>
          <word number="1395342" pos="PRCL">лишь</word>
          <word number="1395343" pos="NOUN">изменник</word>
        </line>
        <line number="12">
          <word number="1395344" pos="PREP">Средь</word>
          <word number="1395345" pos="PRTF">измененных</word>
          <word number="1395346" pos="NOUN">лиц</word>
          <word number="1395347" pos="None">.</word>
        </line>
      </stanza>
      <stanza number="4">
        <line number="13">
          <word number="1395348" pos="CONJ">Но</word>
          <word number="1395349" pos="VERB">медлит</word>
          <word number="1395350" pos="PRCL">лишь</word>
          <word number="1395351" pos="ADJF">бессильный</word>
        </line>
        <line number="14">
          <word number="1395352" pos="PREP">В</word>
          <word number="1395353" pos="NOUN">окованности</word>
          <word number="1395354" pos="NOUN">дней</word>
          <word number="1395355" pos="None">,</word>
        </line>
        <line number="15">
          <word number="1395356" pos="ADVB">Где</word>
          <word number="1395357" pos="NOUN">путь</word>
          <word number="1395358" pos="VERB">простерся</word>
          <word number="1395359" pos="ADJF">пыльный</word>
          <word number="1395360" pos="None">,</word>
        </line>
        <line number="16">
          <word number="1395361" pos="ADVB">Где</word>
          <word number="1395362" pos="COMP">больше</word>
          <word number="1395363" pos="PRED">нет</word>
          <word number="1395364" pos="NOUN">стеблей</word>
          <word number="1395365" pos="None">.</word>
        </line>
      </stanza>
      <stanza number="5">
        <line number="17">
          <word number="1395366" pos="NPRO">Я</word>
          <word number="1395367" pos="ADVB">никогда</word>
          <word number="1395368" pos="PRCL">не</word>
          <word number="1395369" pos="NOUN">ленник</word>
        </line>
        <line number="18">
          <word number="1395370" pos="ADJF">Нецарственных</word>
          <word number="1395371" pos="NOUN">цариц</word>
          <word number="1395372" pos="None">.</word>
        </line>
        <line number="19">
          <word number="1395373" pos="CONJ">И</word>
          <word number="1395374" pos="PRED">нет</word>
          <word number="1395375" pos="None">,</word>
          <word number="1395376" pos="NPRO">я</word>
          <word number="1395377" pos="PRCL">не</word>
          <word number="1395378" pos="NOUN">изменник</word>
          <word number="1395379" pos="None">,</word>
        </line>
        <line number="20">
          <word number="1395380" pos="NPRO">Я</word>
          <word number="1395381" pos="NOUN">птица</word>
          <word number="1395382" pos="PREP">между</word>
          <word number="1395383" pos="NOUN">птиц</word>
          <word number="1395384" pos="None">.</word>
        </line>
      </stanza>
    </poem>
  </text>
</results>
