<?xml version="1.0" encoding="utf-8"?>
        <?xml-stylesheet type="text/xsl" href="style.xslt"?>
<results>
  <text>
    <info>
      <title>ОПЯТЬ ВЕСНА
</title>
      <name>Борис</name>
      <author>Пастернак</author>
    </info>
    <poem>
      <stanza number="1">
        <line number="1">
          <word number="1252972" pos="NOUN">Поезд</word>
          <word number="1252973" pos="VERB">ушел</word>
          <word number="1252974" pos="None">.</word>
          <word number="1252975" pos="VERB">Насыпь</word>
          <word number="1252976" pos="ADJS">черна</word>
          <word number="1252977" pos="None">.</word>
        </line>
        <line number="2">
          <word number="1252978" pos="ADVB">Где</word>
          <word number="1252979" pos="NPRO">я</word>
          <word number="1252980" pos="NOUN">дорогу</word>
          <word number="1252981" pos="ADVB">впотьмах</word>
          <word number="1252982" pos="VERB">раздобуду</word>
          <word number="1252983" pos="None">?</word>
        </line>
        <line number="3">
          <word number="1252984" pos="ADJF">Неузнаваемая</word>
          <word number="1252985" pos="NOUN">сторона</word>
          <word number="1252986" pos="None">,</word>
        </line>
        <line number="4">
          <word number="1252987" pos="CONJ">Хоть</word>
          <word number="1252988" pos="NPRO">я</word>
          <word number="1252989" pos="CONJ">и</word>
          <word number="1252990" pos="NOUN">сутки</word>
          <word number="1252991" pos="PRCL">только</word>
          <word number="1252992" pos="ADVB">отсюда</word>
          <word number="1252993" pos="None">.</word>
        </line>
        <line number="5">
          <word number="1252994" pos="VERB">Замер</word>
          <word number="1252995" pos="PREP">на</word>
          <word number="1252996" pos="NOUN">шпалах</word>
          <word number="1252997" pos="NOUN">лязг</word>
          <word number="1252998" pos="NOUN">чугуна</word>
          <word number="1252999" pos="None">.</word>
        </line>
        <line number="6">
          <word number="1253000" pos="ADVB">Вдруг</word>
          <word number="1253001" pos="None">—</word>
          <word number="1253002" pos="CONJ">что</word>
          <word number="1253003" pos="PREP">за</word>
          <word number="1253004" pos="ADJF">новая</word>
          <word number="1253005" pos="None">,</word>
          <word number="1253006" pos="NOUN">право</word>
          <word number="1253007" pos="None">,</word>
          <word number="1253008" pos="NOUN">причуда</word>
          <word number="1253009" pos="None">:</word>
        </line>
        <line number="7">
          <word number="1253010" pos="NOUN">Сутолка</word>
          <word number="1253011" pos="None">,</word>
          <word number="1253012" pos="NOUN">кумушек</word>
          <word number="1253013" pos="NOUN">пересуды</word>
          <word number="1253014" pos="None">.</word>
        </line>
        <line number="8">
          <word number="1253015" pos="CONJ">Что</word>
          <word number="1253016" pos="NPRO">их</word>
          <word number="1253017" pos="VERB">попутал</word>
          <word number="1253018" pos="PREP">за</word>
          <word number="1253019" pos="NOUN">сатана</word>
          <word number="1253020" pos="None">?</word>
        </line>
      </stanza>
      <stanza number="2">
        <line number="9">
          <word number="1253021" pos="ADVB">Где</word>
          <word number="1253022" pos="NPRO">я</word>
          <word number="1253023" pos="NOUN">обрывки</word>
          <word number="1253024" pos="ADJF">этих</word>
          <word number="1253025" pos="NOUN">речей</word>
        </line>
        <line number="10">
          <word number="1253026" pos="VERB">Слышал</word>
          <word number="1253027" pos="ADVB">уж</word>
          <word number="1253028" pos="CONJ">как</word>
          <word number="1253029" pos="None">-</word>
          <word number="1253030" pos="CONJ">то</word>
          <word number="1253031" pos="ADVB">порой</word>
          <word number="1253032" pos="ADJF">прошлогодней</word>
          <word number="1253033" pos="None">?</word>
        </line>
        <line number="11">
          <word number="1253034" pos="INTJ">Ах</word>
          <word number="1253035" pos="None">,</word>
          <word number="1253036" pos="PRCL">это</word>
          <word number="1253037" pos="ADVB">сызнова</word>
          <word number="1253038" pos="None">,</word>
          <word number="1253039" pos="CONJ">верно</word>
          <word number="1253040" pos="None">,</word>
          <word number="1253041" pos="ADVB">сегодня</word>
        </line>
        <line number="12">
          <word number="1253042" pos="VERB">Вышел</word>
          <word number="1253043" pos="PREP">из</word>
          <word number="1253044" pos="NOUN">рощи</word>
          <word number="1253045" pos="ADVB">ночью</word>
          <word number="1253046" pos="NOUN">ручей</word>
          <word number="1253047" pos="None">.</word>
        </line>
        <line number="13">
          <word number="1253048" pos="PRCL">Это</word>
          <word number="1253049" pos="None">,</word>
          <word number="1253050" pos="CONJ">как</word>
          <word number="1253051" pos="PREP">в</word>
          <word number="1253052" pos="ADJF">прежние</word>
          <word number="1253053" pos="NOUN">времена</word>
          <word number="1253054" pos="None">,</word>
        </line>
        <line number="14">
          <word number="1253055" pos="VERB">Сдвинула</word>
          <word number="1253056" pos="NOUN">льдины</word>
          <word number="1253057" pos="CONJ">и</word>
          <word number="1253058" pos="VERB">вздулась</word>
          <word number="1253059" pos="NOUN">запруда</word>
          <word number="1253060" pos="None">.</word>
        </line>
        <line number="15">
          <word number="1253061" pos="PRCL">Это</word>
          <word number="1253062" pos="ADVB">поистине</word>
          <word number="1253063" pos="NOUN">новое</word>
          <word number="1253064" pos="NOUN">чудо</word>
          <word number="1253065" pos="None">,</word>
        </line>
        <line number="16">
          <word number="1253066" pos="PRCL">Это</word>
          <word number="1253067" pos="None">,</word>
          <word number="1253068" pos="CONJ">как</word>
          <word number="1253069" pos="ADVB">прежде</word>
          <word number="1253070" pos="None">,</word>
          <word number="1253071" pos="ADVB">снова</word>
          <word number="1253072" pos="NOUN">весна</word>
          <word number="1253073" pos="None">.</word>
        </line>
      </stanza>
      <stanza number="3">
        <line number="17">
          <word number="1253074" pos="PRCL">Это</word>
          <word number="1253075" pos="NPRO">она</word>
          <word number="1253076" pos="None">,</word>
          <word number="1253077" pos="PRCL">это</word>
          <word number="1253078" pos="NPRO">она</word>
          <word number="1253079" pos="None">,</word>
        </line>
        <line number="18">
          <word number="1253080" pos="PRCL">Это</word>
          <word number="1253081" pos="NPRO">ее</word>
          <word number="1253082" pos="NOUN">чародейство</word>
          <word number="1253083" pos="CONJ">и</word>
          <word number="1253084" pos="NOUN">диво</word>
          <word number="1253085" pos="None">,</word>
        </line>
        <line number="19">
          <word number="1253086" pos="PRCL">Это</word>
          <word number="1253087" pos="NPRO">ее</word>
          <word number="1253088" pos="NOUN">телогрейка</word>
          <word number="1253089" pos="PREP">за</word>
          <word number="1253090" pos="NOUN">ивой</word>
          <word number="1253091" pos="None">,</word>
        </line>
        <line number="20">
          <word number="1253092" pos="NOUN">Плечи</word>
          <word number="1253093" pos="None">,</word>
          <word number="1253094" pos="NOUN">косынка</word>
          <word number="1253095" pos="None">,</word>
          <word number="1253096" pos="NOUN">стан</word>
          <word number="1253097" pos="CONJ">и</word>
          <word number="1253098" pos="NOUN">спина</word>
          <word number="1253099" pos="None">.</word>
        </line>
        <line number="21">
          <word number="1253100" pos="PRCL">Это</word>
          <word number="1253101" pos="NOUN">Снегурка</word>
          <word number="1253102" pos="PREP">у</word>
          <word number="1253103" pos="NOUN">края</word>
          <word number="1253104" pos="NOUN">обрыва</word>
          <word number="1253105" pos="None">.</word>
        </line>
        <line number="22">
          <word number="1253106" pos="PRCL">Это</word>
          <word number="1253107" pos="PREP">о</word>
          <word number="1253108" pos="NPRO">ней</word>
          <word number="1253109" pos="PREP">из</word>
          <word number="1253110" pos="NOUN">оврага</word>
          <word number="1253111" pos="PREP">со</word>
          <word number="1253112" pos="NOUN">дна</word>
        </line>
        <line number="23">
          <word number="1253113" pos="VERB">Льется</word>
          <word number="1253114" pos="PREP">без</word>
          <word number="1253115" pos="NOUN">умолку</word>
          <word number="1253116" pos="NOUN">бред</word>
          <word number="1253117" pos="ADJF">торопливый</word>
        </line>
        <line number="24">
          <word number="1253118" pos="ADJF">Полубезумного</word>
          <word number="1253119" pos="NOUN">болтуна</word>
          <word number="1253120" pos="None">.</word>
        </line>
      </stanza>
      <stanza number="4">
        <line number="25">
          <word number="1253121" pos="PRCL">Это</word>
          <word number="1253122" pos="PREP">пред</word>
          <word number="1253123" pos="NPRO">ней</word>
          <word number="1253124" pos="None">,</word>
          <word number="1253125" pos="GRND">заливая</word>
          <word number="1253126" pos="NOUN">преграды</word>
          <word number="1253127" pos="None">,</word>
        </line>
        <line number="26">
          <word number="1253128" pos="VERB">Тонет</word>
          <word number="1253129" pos="PREP">в</word>
          <word number="1253130" pos="NOUN">чаду</word>
          <word number="1253131" pos="ADJF">водяном</word>
          <word number="1253132" pos="NOUN">быстрина</word>
          <word number="1253133" pos="None">,</word>
        </line>
        <line number="27">
          <word number="1253134" pos="NOUN">Лампой</word>
          <word number="1253135" pos="ADJF">висячего</word>
          <word number="1253136" pos="NOUN">водопада</word>
        </line>
        <line number="28">
          <word number="1253137" pos="PREP">К</word>
          <word number="1253138" pos="NOUN">круче</word>
          <word number="1253139" pos="PREP">с</word>
          <word number="1253140" pos="NOUN">шипеньем</word>
          <word number="1253141" pos="PRTS">пригвождена</word>
          <word number="1253142" pos="None">.</word>
        </line>
        <line number="29">
          <word number="1253143" pos="PRCL">Это</word>
          <word number="1253144" pos="None">,</word>
          <word number="1253145" pos="NOUN">зубами</word>
          <word number="1253146" pos="GRND">стуча</word>
          <word number="1253147" pos="PREP">от</word>
          <word number="1253148" pos="NOUN">простуды</word>
          <word number="1253149" pos="None">,</word>
        </line>
        <line number="30">
          <word number="1253150" pos="VERB">Льется</word>
          <word number="1253151" pos="PREP">чрез</word>
          <word number="1253152" pos="NOUN">край</word>
          <word number="1253153" pos="ADJF">ледяная</word>
          <word number="1253154" pos="GRND">струя</word>
        </line>
        <line number="31">
          <word number="1253155" pos="PREP">В</word>
          <word number="1253156" pos="NOUN">пруд</word>
          <word number="1253157" pos="CONJ">и</word>
          <word number="1253158" pos="PREP">из</word>
          <word number="1253159" pos="NOUN">пруда</word>
          <word number="1253160" pos="PREP">в</word>
          <word number="1253161" pos="ADJF">другую</word>
          <word number="1253162" pos="NOUN">посуду</word>
          <word number="1253163" pos="None">.</word>
        </line>
        <line number="32">
          <word number="1253164" pos="NOUN">Речь</word>
          <word number="1253165" pos="NOUN">половодья</word>
          <word number="1253166" pos="None">—</word>
          <word number="1253167" pos="NOUN">бред</word>
          <word number="1253168" pos="NOUN">бытия</word>
          <word number="1253169" pos="None">.</word>
        </line>
      </stanza>
    </poem>
  </text>
</results>
