<?xml version="1.0" encoding="utf-8"?>
    <?xml-stylesheet type="text/xsl" href="style.xslt"?>
<results>
  <text>
    <info>
      <title></title>
      <name>Георгий</name>
      <author>Иванов</author>
    </info>
    <poem>
      <stanza number="1">
        <line number="1">
          <word number="1063975" pos="NOUN">Образ</word>
          <word number="1063976" pos="PRTF">полусотворенный</word>
          <word number="1063977" pos="None">,</word>
        </line>
        <line number="2">
          <word number="1063978" pos="NOUN">Шопот</word>
          <word number="1063979" pos="PRTF">недоговоренный</word>
          <word number="1063980" pos="None">,</word>
        </line>
        <line number="3">
          <word number="1063981" pos="NOUN">Полужизнь</word>
          <word number="1063982" pos="None">,</word>
          <word number="1063983" pos="NOUN">полуусталость</word>
          <word number="1063984" pos="PNCT">—</word>
        </line>
        <line number="4">
          <word number="1063985" pos="PRCL">Это</word>
          <word number="1063986" pos="ADJF">все</word>
          <word number="1063987" pos="None">,</word>
          <word number="1063988" pos="CONJ">что</word>
          <word number="1063989" pos="NPRO">мне</word>
          <word number="1063990" pos="VERB">осталось</word>
          <word number="1063991" pos="None">.</word>
        </line>
      </stanza>
      <stanza number="2">
        <line number="5">
          <word number="1063992" pos="VERB">Принимаю</word>
          <word number="1063993" pos="None">,</word>
          <word number="1063994" pos="CONJ">как</word>
          <word number="1063995" pos="NOUN">награду</word>
          <word number="1063996" pos="None">,</word>
        </line>
        <line number="6">
          <word number="1063997" pos="NOUN">Тень</word>
          <word number="1063998" pos="None">,</word>
          <word number="1063999" pos="ADJF">скользящую</word>
          <word number="1064000" pos="PREP">по</word>
          <word number="1064001" pos="NOUN">саду</word>
          <word number="1064002" pos="None">,</word>
        </line>
        <line number="7">
          <word number="1064003" pos="NOUN">Переход</word>
          <word number="1064004" pos="NOUN">апреля</word>
          <word number="1064005" pos="PREP">к</word>
          <word number="1064006" pos="NOUN">маю</word>
          <word number="1064007" pos="None">,</word>
        </line>
        <line number="8">
          <word number="1064008" pos="CONJ">Как</word>
          <word number="1064009" pos="NOUN">подарок</word>
          <word number="1064010" pos="None">,</word>
          <word number="1064011" pos="VERB">принимаю</word>
          <word number="1064012" pos="None">.</word>
        </line>
      </stanza>
    </poem>
  </text>
</results>
