<?xml version="1.0" encoding="utf-8"?>
    <?xml-stylesheet type="text/xsl" href="style.xslt"?>
<results>
  <text>
    <info>
      <title></title>
      <name>Максимилиан</name>
      <author>Волошин</author>
    </info>
    <poem>
      <stanza number="1">
        <line number="1">
          <word number="1099736" pos="NPRO">Ты</word>
          <word number="1099737" pos="VERB">живешь</word>
          <word number="1099738" pos="PREP">в</word>
          <word number="1099739" pos="NOUN">молчаньи</word>
          <word number="1099740" pos="ADJF">темных</word>
          <word number="1099741" pos="NOUN">комнат</word>
        </line>
        <line number="2">
          <word number="1099742" pos="PREP">Средь</word>
          <word number="1099743" pos="NOUN">шелков</word>
          <word number="1099744" pos="CONJ">и</word>
          <word number="1099745" pos="ADJF">тусклой</word>
          <word number="1099746" pos="NOUN">позолоты</word>
          <word number="1099747" pos="None">,</word>
        </line>
        <line number="3">
          <word number="1099748" pos="ADVB">Где</word>
          <word number="1099749" pos="ADJF">твой</word>
          <word number="1099750" pos="NOUN">взгляд</word>
          <word number="1099751" pos="VERB">несут</word>
          <word number="1099752" pos="PREP">в</word>
          <word number="1099753" pos="NPRO">себе</word>
          <word number="1099754" pos="CONJ">и</word>
          <word number="1099755" pos="VERB">помнят</word>
        </line>
        <line number="4">
          <word number="1099756" pos="NOUN">Зеркала</word>
          <word number="1099757" pos="None">,</word>
          <word number="1099758" pos="NOUN">картины</word>
          <word number="1099759" pos="CONJ">и</word>
          <word number="1099760" pos="NOUN">киоты</word>
          <word number="1099761" pos="None">.</word>
        </line>
      </stanza>
      <stanza number="2">
        <line number="5">
          <word number="1099762" pos="VERB">Смотрят</word>
          <word number="1099763" pos="PREP">в</word>
          <word number="1099764" pos="VERB">душу</word>
          <word number="1099765" pos="ADJF">строгие</word>
          <word number="1099766" pos="NOUN">портреты</word>
          <word number="1099767" pos="None">...</word>
        </line>
        <line number="6">
          <word number="1099768" pos="NOUN">Речи</word>
          <word number="1099769" pos="NOUN">книг</word>
          <word number="1099770" pos="VERB">звучат</word>
          <word number="1099771" pos="ADVB">темно</word>
          <word number="1099772" pos="CONJ">и</word>
          <word number="1099773" pos="ADVB">разно</word>
          <word number="1099774" pos="None">...</word>
        </line>
        <line number="7">
          <word number="1099775" pos="VERB">Любишь</word>
          <word number="1099776" pos="NPRO">ты</word>
          <word number="1099777" pos="NOUN">вериги</word>
          <word number="1099778" pos="CONJ">и</word>
          <word number="1099779" pos="NOUN">запреты</word>
          <word number="1099780" pos="None">,</word>
        </line>
        <line number="8">
          <word number="1099781" pos="NOUN">Грех</word>
          <word number="1099782" pos="NOUN">молитв</word>
          <word number="1099783" pos="CONJ">и</word>
          <word number="1099784" pos="NOUN">таинства</word>
          <word number="1099785" pos="NOUN">соблазна</word>
          <word number="1099786" pos="None">.</word>
        </line>
      </stanza>
      <stanza number="3">
        <line number="9">
          <word number="1099787" pos="CONJ">И</word>
          <word number="1099788" pos="NPRO">тебе</word>
          <word number="1099789" pos="ADJS">мучительно</word>
          <word number="1099790" pos="ADJS">знакомы</word>
        </line>
        <line number="10">
          <word number="1099791" pos="ADJF">Сладкий</word>
          <word number="1099792" pos="NOUN">дым</word>
          <word number="1099793" pos="NOUN">бензоя</word>
          <word number="1099794" pos="None">,</word>
          <word number="1099795" pos="NOUN">запах</word>
          <word number="1099796" pos="NOUN">нарда</word>
          <word number="1099797" pos="None">,</word>
        </line>
        <line number="11">
          <word number="1099798" pos="NOUN">Тонкость</word>
          <word number="1099799" pos="NOUN">рук</word>
          <word number="1099800" pos="PREP">у</word>
          <word number="1099801" pos="NOUN">юношей</word>
          <word number="1099802" pos="NOUN">Содомы</word>
          <word number="1099803" pos="None">,</word>
        </line>
        <line number="12">
          <word number="1099804" pos="NOUN">Змийность</word>
          <word number="1099805" pos="NOUN">уст</word>
          <word number="1099806" pos="PREP">у</word>
          <word number="1099807" pos="NOUN">женщин</word>
          <word number="1099808" pos="NOUN">Леонардо</word>
          <word number="1099809" pos="None">...</word>
        </line>
      </stanza>
    </poem>
  </text>
</results>
